impipy/__init__.py
impipy/importance.py
impipy/tree_importance.py
impipy-0.1.1.dist-info/METADATA
impipy-0.1.1.dist-info/WHEEL
impipy-0.1.1.dist-info/top_level.txt
impipy-0.1.1.dist-info/RECORD
