Metadata-Version: 2.1
Name: impipy
Version: 0.1.1
Summary: This library provides tools for calculating feature importance in machine learning models.
Home-page: UNKNOWN
Author: Witali Bułatow
License: UNKNOWN
Platform: UNKNOWN
Requires-Dist: numpy (==1.22.3)
Requires-Dist: pandas (==1.4.2)
Requires-Dist: matplotlib (==3.5.1)
Requires-Dist: seaborn (==0.11.2)
Requires-Dist: scikit-learn (==1.1.3)
Requires-Dist: tqdm (==4.64.0)
